{
  "headers": {
    "x-content-type-options": "nosniff",
    "age": "1741",
    "cf-ray": "603bf5f62a18cb0c-ARN",
    "vary": "Accept-Encoding",
    "timing-allow-origin": "*",
    "strict-transport-security": "max-age=31536000; includeSubDomains; preload",
    "date": "Fri, 18 Dec 2020 21:26:12 GMT",
    "x-cache": "MISS, MISS",
    "cf-cache-status": "HIT",
    "cf-request-id": "0719580ddc0000cb0cf798a000000001",
    "access-control-allow-origin": "*",
    "expect-ct": "max-age=604800, report-uri=\"https://report-uri.cloudflare.com/cdn-cgi/beacon/expect-ct\"",
    "server": "cloudflare",
    "cross-origin-resource-policy": "cross-origin",
    "content-type": "application/javascript; charset=utf-8",
    "access-control-expose-headers": "*",
    "cache-control": "public, max-age=31536000, s-maxage=31536000, immutable",
    "x-served-by": "cache-fra19126-FRA, cache-bma1631-BMA",
    "etag": "W/\"1590-kbC/A8tU5u43Q+n1XbP7CrzHRtc\""
  },
  "url": "https://cdn.jsdelivr.net/gh/ekmwest/side@3.0.0/side_build.js"
}