{
  "headers": {
    "set-cookie": "__cfduid=d9dfc4fddc467ad02853c087860907fce1608495234; expires=Tue, 19-Jan-21 20:13:54 GMT; path=/; domain=.deno.land; HttpOnly; SameSite=Lax; Secure",
    "cf-cache-status": "HIT",
    "x-amz-version-id": ".qaIQJxCM8HYSGIN734jsyTQnqcQnBKI",
    "report-to": "{\"endpoints\":[{\"url\":\"https:\\/\\/a.nel.cloudflare.com\\/report?s=1CYu6hhGRhYmRNwfdVjx8tYvzEP0R7xi2SYnmvvGMSCZbKDF67HhS3OJZxQHK1LpHsSxTCGi%2F8XyhwE5rnVY1F3kRk24CUBbgsQ%3D\"}],\"group\":\"cf-nel\",\"max_age\":604800}",
    "nel": "{\"report_to\":\"cf-nel\",\"max_age\":604800}",
    "server": "cloudflare",
    "accept-ranges": "bytes",
    "x-amz-id-2": "Rk/wxuuhQfB7ZxDlMhHAkyQcF/sU2+EVLqCmY10XlR7I1WHBhZ2XoraDLlX+D14w/HNXR4CyiPI=",
    "etag": "\"c6efa2db22fb59568a75acd32362c5bb\"",
    "last-modified": "Mon, 14 Dec 2020 20:26:14 GMT",
    "date": "Sun, 20 Dec 2020 20:13:54 GMT",
    "x-amz-request-id": "5F9E58C92B4E6BD9",
    "content-length": "729",
    "vary": "Accept-Encoding",
    "cache-control": "public, max-age=31536000, immutable",
    "access-control-allow-origin": "*",
    "content-type": "application/typescript; charset=utf-8",
    "expect-ct": "max-age=604800, report-uri=\"https://report-uri.cloudflare.com/cdn-cgi/beacon/expect-ct\"",
    "cf-ray": "604c06cf1c04cad4-ARN",
    "age": "495483",
    "cf-request-id": "07236295710000cad4f98d4000000001"
  },
  "url": "https://deno.land/std@0.81.0/path/mod.ts"
}