{
  "headers": {
    "content-length": "13245",
    "cache-control": "public, max-age=31536000, immutable",
    "report-to": "{\"endpoints\":[{\"url\":\"https:\\/\\/a.nel.cloudflare.com\\/report?s=lmbOzy17qRJe8DU7x9%2B1O83toY%2B4XiHsddrparMBxQgnLi785W4xcKIQWI29kkpdJu6AN2EN2LcJLYnEHSQ2R5YF2FL8c6MHFkc%3D\"}],\"group\":\"cf-nel\",\"max_age\":604800}",
    "cf-request-id": "072362975c0000cad406bc9000000001",
    "etag": "\"d2bbdb5faa67f6b84669428c8b605c8d\"",
    "x-amz-id-2": "Y3xG2tIFvFLVScHQFrbNcSzrD2Oauf1oiuECQoxWemOhpSvCQPk02hSxo2gCl0hoN6vwMvcdu5c=",
    "last-modified": "Mon, 14 Dec 2020 20:26:14 GMT",
    "x-amz-version-id": "PMmb7zjOm85Cj61fU_LSF6n1Hib5XFJp",
    "cf-cache-status": "HIT",
    "access-control-allow-origin": "*",
    "nel": "{\"report_to\":\"cf-nel\",\"max_age\":604800}",
    "vary": "Accept-Encoding",
    "cf-ray": "604c06d22b47cad4-ARN",
    "content-type": "application/typescript; charset=utf-8",
    "expect-ct": "max-age=604800, report-uri=\"https://report-uri.cloudflare.com/cdn-cgi/beacon/expect-ct\"",
    "x-amz-request-id": "AE895A44A74D3D89",
    "age": "2006",
    "server": "cloudflare",
    "date": "Sun, 20 Dec 2020 20:13:54 GMT",
    "set-cookie": "__cfduid=d9dfc4fddc467ad02853c087860907fce1608495234; expires=Tue, 19-Jan-21 20:13:54 GMT; path=/; domain=.deno.land; HttpOnly; SameSite=Lax; Secure",
    "accept-ranges": "bytes"
  },
  "url": "https://deno.land/std@0.81.0/hash/sha1.ts"
}