{
  "headers": {
    "accept-ranges": "bytes",
    "x-amz-request-id": "D13D4C94C05DC1E7",
    "vary": "Accept-Encoding",
    "cf-ray": "5f8eb13b2d57f162-ARN",
    "expect-ct": "max-age=604800, report-uri=\"https://report-uri.cloudflare.com/cdn-cgi/beacon/expect-ct\"",
    "x-amz-id-2": "6DIRoCJP7dM0ji1fQO15GNOejHvUBF+xKsgukYLywzcFVPq5SiU/82ciWIl27x3QmIXo3/f63QM=",
    "x-amz-version-id": "k5jiryfe_Br.pzTQuOrfls2Nt_.YhQCm",
    "content-type": "application/typescript; charset=utf-8",
    "access-control-allow-origin": "*",
    "content-length": "279",
    "cf-cache-status": "HIT",
    "cache-control": "public, max-age=31536000, immutable",
    "set-cookie": "__cfduid=d3b8f1a1c6fc4158f17a786fd76eedba81606509920; expires=Sun, 27-Dec-20 20:45:20 GMT; path=/; domain=.deno.land; HttpOnly; SameSite=Lax; Secure",
    "date": "Fri, 27 Nov 2020 20:45:20 GMT",
    "etag": "\"f9fa4cd7b2bb4f700809c4df7a2cac2a\"",
    "nel": "{\"report_to\":\"cf-nel\",\"max_age\":604800}",
    "age": "85",
    "last-modified": "Mon, 23 Nov 2020 14:12:13 GMT",
    "cf-request-id": "06ad0d18f90000f162a90c8000000001",
    "report-to": "{\"endpoints\":[{\"url\":\"https:\\/\\/a.nel.cloudflare.com\\/report?s=yq4V6TQq2iCWAu4coOEZULxocVlyPriR5IzUt%2FH%2Bl4IfC7SHlUXV4xus239b%2Bv3x7jgD%2FTf3Hu96m5IP9dkOsbSeQFdkBXEbbnY%3D\"}],\"group\":\"cf-nel\",\"max_age\":604800}",
    "server": "cloudflare"
  },
  "url": "https://deno.land/std@0.79.0/async/delay.ts"
}