{
  "headers": {
    "content-length": "732",
    "access-control-allow-origin": "*",
    "expect-ct": "max-age=604800, report-uri=\"https://report-uri.cloudflare.com/cdn-cgi/beacon/expect-ct\"",
    "etag": "\"de4b83ca5340f1e9c133dc131e28f5c5\"",
    "nel": "{\"report_to\":\"cf-nel\",\"max_age\":604800}",
    "vary": "Accept-Encoding",
    "content-type": "application/typescript; charset=utf-8",
    "x-amz-request-id": "122E560F4F90DC8C",
    "last-modified": "Mon, 14 Dec 2020 20:26:14 GMT",
    "accept-ranges": "bytes",
    "set-cookie": "__cfduid=d9dfc4fddc467ad02853c087860907fce1608495234; expires=Tue, 19-Jan-21 20:13:54 GMT; path=/; domain=.deno.land; HttpOnly; SameSite=Lax; Secure",
    "age": "2005",
    "cf-cache-status": "HIT",
    "date": "Sun, 20 Dec 2020 20:13:54 GMT",
    "x-amz-id-2": "wj0aWoi4U14pDUQ2vwwAX9Khxsq6K5RNeAaMp/ZiJR680+0OzrC7h2g/aGGBV+n2BrUsYHo45mY=",
    "report-to": "{\"endpoints\":[{\"url\":\"https:\\/\\/a.nel.cloudflare.com\\/report?s=D5jNpoAsnm1SzCDswexeV2aLaTAWZ5KwphqFuiGIhhzG3nk7iWrN3jL15nJTqt%2B7H%2Ftz2k5W0oJxtFhzSx2Cx3tlNIWbhZErY0w%3D\"}],\"group\":\"cf-nel\",\"max_age\":604800}",
    "server": "cloudflare",
    "x-amz-version-id": "q7o3pfjUcIz5q.USFc4rgQBNqphHBd5Z",
    "cache-control": "public, max-age=31536000, immutable",
    "cf-request-id": "07236295c00000cad457ba8000000001",
    "cf-ray": "604c06cf9d55cad4-ARN"
  },
  "url": "https://deno.land/std@0.81.0/path/_interface.ts"
}