{
  "headers": {
    "last-modified": "Wed, 20 Jan 2021 05:26:03 GMT",
    "access-control-allow-origin": "*",
    "expect-ct": "max-age=604800, report-uri=\"https://report-uri.cloudflare.com/cdn-cgi/beacon/expect-ct\"",
    "x-amz-version-id": "mtBMP6dEbJtvE4lJGYFTcLcDIH85aKFM",
    "etag": "\"39a6e3eb5ed9b03e29f162122aa1a562\"",
    "content-length": "21917",
    "cf-cache-status": "HIT",
    "server": "cloudflare",
    "content-type": "application/typescript; charset=utf-8",
    "age": "459831",
    "set-cookie": "__cfduid=d06b8749a1151d32c8c8b97eea8e2b47f1611904466; expires=Sun, 28-Feb-21 07:14:26 GMT; path=/; domain=.deno.land; HttpOnly; SameSite=Lax; Secure",
    "x-amz-id-2": "ael/AqUQ57BObXcpcc39bldPSLS6ZQ9ILUwUvyR1E5KVY7QYJjjIK786jZjZvqx9MgJ0OgWr99g=",
    "cf-ray": "619128018d0bf152-ARN",
    "report-to": "{\"max_age\":604800,\"endpoints\":[{\"url\":\"https:\\/\\/a.nel.cloudflare.com\\/report?s=cTPYkfxKjq5bDATpq6DrFdRVQTiXPTw73rE7BwyfKULFjNlHGgeb2zlWwZwKoltZ%2FBhjz6ovsDO8QpTJ7Tl97pVKe6qjaMh4Q2E%3D\"}],\"group\":\"cf-nel\"}",
    "cache-control": "public, max-age=31536000, immutable",
    "nel": "{\"report_to\":\"cf-nel\",\"max_age\":604800}",
    "x-amz-request-id": "D8C378BCE114CFAD",
    "accept-ranges": "bytes",
    "cf-request-id": "07ee9754f90000f152a387b000000001",
    "date": "Fri, 29 Jan 2021 07:14:26 GMT",
    "vary": "Accept-Encoding"
  },
  "url": "https://deno.land/std@0.84.0/io/bufio.ts"
}